setup.cfg
setup.py
bayesianfridge/__init__.py
bayesianfridge/smc.py
bayesianfridge.egg-info/PKG-INFO
bayesianfridge.egg-info/SOURCES.txt
bayesianfridge.egg-info/dependency_links.txt
bayesianfridge.egg-info/requires.txt
bayesianfridge.egg-info/top_level.txt