Metadata-Version: 1.1
Name: bayesianfridge
Version: 1.0
Summary: Sequential Monte Carlo sampler for PyMC2 models.
Home-page: https://github.com/christophmark/bayesianfridge
Author: Christoph Mark
Author-email: christoph.mark@fau.de
License: The MIT License (MIT)
Download-URL: https://github.com/christophmark/bayesianfridge/tarball/1.0
Keywords: SMC,MCMC,Monte Carlo,Metropolis,annealing,marginal likelihood,model evidence
Platform: UNKNOWN
